deepvisiontools/__init__.py
deepvisiontools/config/__init__.py
deepvisiontools/config/config.py
deepvisiontools/config/errors.py
deepvisiontools/data/__init__.py
deepvisiontools/data/additional_augmentations.py
deepvisiontools/data/augmentation_class.py
deepvisiontools/data/batch_augmentations.py
deepvisiontools/data/dataset.py
deepvisiontools/data/errors.py
deepvisiontools/data/data_reader/__init__.py
deepvisiontools/data/data_reader/readers.py
deepvisiontools/formats/__init__.py
deepvisiontools/formats/base_data.py
deepvisiontools/formats/base_formats.py
deepvisiontools/formats/errors.py
deepvisiontools/formats/formats.py
deepvisiontools/formats/utils.py
deepvisiontools/inference/__init__.py
deepvisiontools/inference/evaluator.py
deepvisiontools/inference/patchifier.py
deepvisiontools/inference/predictor.py
deepvisiontools/metrics/__init__.py
deepvisiontools/metrics/available_metrics.py
deepvisiontools/metrics/base_metric.py
deepvisiontools/metrics/func.py
deepvisiontools/metrics/matcher.py
deepvisiontools/metrics/utils.py
deepvisiontools/models/__init__.py
deepvisiontools/models/basemodel.py
deepvisiontools/models/mask2former/__init__.py
deepvisiontools/models/mask2former/mask2former.py
deepvisiontools/models/smp/__init__.py
deepvisiontools/models/smp/errors.py
deepvisiontools/models/smp/smp.py
deepvisiontools/models/timmyolo/__init__.py
deepvisiontools/models/timmyolo/errors.py
deepvisiontools/models/timmyolo/timmyolo.py
deepvisiontools/models/timmyolo/utils.py
deepvisiontools/models/yolo/__init__.py
deepvisiontools/models/yolo/errors.py
deepvisiontools/models/yolo/utils.py
deepvisiontools/models/yolo/yolo.py
deepvisiontools/models/yoloseg/__init__.py
deepvisiontools/models/yoloseg/errors.py
deepvisiontools/models/yoloseg/utils.py
deepvisiontools/models/yoloseg/yoloseg.py
deepvisiontools/preprocessing/__init__.py
deepvisiontools/preprocessing/image.py
deepvisiontools/preprocessing/preprocessing.py
deepvisiontools/train/__init__.py
deepvisiontools-0.2.0.dist-info/licenses/LICENSE.txt
deepvisiontools-0.2.0.dist-info/METADATA
deepvisiontools-0.2.0.dist-info/WHEEL
deepvisiontools-0.2.0.dist-info/top_level.txt
deepvisiontools-0.2.0.dist-info/RECORD
