Metadata-Version: 2.4
Name: deepvisiontools
Version: 0.2.0
Summary: Overlay of PyTorch to generalize trainning and inference processes for detection, instance segmentation and semantic segmentation tasks.
Author-email: Lucas Bernigaud Samatan <lucas.bernigaud-samatan@inrae.fr>, Jordan Bernigaud Samatan <jordan.bernigaud-samatan@inrae.fr>, Paul Faucher <paul.faucher@inrae.fr>
Maintainer-email: Jordan Bernigaud Samatan <jordan.bernigaud-samatan@inrae.fr>, Lucas Bernigaud Samatan <lucas.bernigaud-samatan@inrae.fr>
License:                     GNU AFFERO GENERAL PUBLIC LICENSE
Project-URL: Homepage, https://forgemia.inra.fr/ue-apc/librairies/python/deepvisiontools_v1
Project-URL: Issues, https://forgemia.inra.fr/ue-apc/librairies/python/deepvisiontools_v1/-/issues
Project-URL: Documentation, https://deepvisiontools.readthedocs.io/en/latest/
Project-URL: Repository, https://forgemia.inra.fr/ue-apc/librairies/python/deepvisiontools_v1
Classifier: Development Status :: 4 - Beta
Classifier: Programming Language :: Python :: 3.11
Classifier: Programming Language :: Python :: 3.12
Requires-Python: <=3.12.12,>=3.11.9
License-File: LICENSE.txt
Requires-Dist: torch<=2.6.0,>=2.4.0
Requires-Dist: torchvision<=0.21.0,>=0.19.0
Requires-Dist: pycocotools==2.0.8
Requires-Dist: torchmetrics<=1.7.0,>=1.4.0
Requires-Dist: tensorboard<=2.19.0,>=2.18.0
Requires-Dist: ultralytics<=8.3.95,>=8.3.28
Requires-Dist: transformers<=4.50.0,>=4.44.2
Requires-Dist: colorcet==3.1.0
Requires-Dist: segmentation-models-pytorch<=0.5.0,>0.4.0
Requires-Dist: openpyxl==3.1.5
Dynamic: license-file
